feature_reduction/ReadWrite_txt.py
feature_reduction/__init__.py
feature_reduction/feature1.py
feature_reduction/feature2.py
feature_reduction/feature3.py
feature_reduction/feature4.py
feature_reduction/rw_txt.py
feature_reduction-3.0.dist-info/DESCRIPTION.rst
feature_reduction-3.0.dist-info/METADATA
feature_reduction-3.0.dist-info/RECORD
feature_reduction-3.0.dist-info/WHEEL
feature_reduction-3.0.dist-info/metadata.json
feature_reduction-3.0.dist-info/top_level.txt
feature_reduction-3.0.dist-info/zip-safe
